viavai/__init__.py
viavai/static/index.html
viavai-0.1.4.dist-info/METADATA
viavai-0.1.4.dist-info/WHEEL
viavai-0.1.4.dist-info/top_level.txt
viavai-0.1.4.dist-info/RECORD
