Metadata-Version: 2.1
Name: viavai
Version: 0.1.4
Summary: A sample Python library called Viavai
Home-page: https://github.com/XLongLink/viavai
Author: Sau1707
Author-email: your.email@example.com
Classifier: Programming Language :: Python :: 3
Classifier: License :: OSI Approved :: MIT License
Classifier: Operating System :: OS Independent
Requires-Python: >=3.11
